iziproxy/__init__.py
iziproxy/config_manager.py
iziproxy/env_detector.py
iziproxy/logger.py
iziproxy/ntlm_auth.py
iziproxy/password_manager.py
iziproxy/proxy_detector.py
iziproxy/proxy_manager.py
iziproxy/secure_config.py
iziproxy-0.6.0.dist-info/licenses/LICENSE
iziproxy-0.6.0.dist-info/METADATA
iziproxy-0.6.0.dist-info/WHEEL
iziproxy-0.6.0.dist-info/top_level.txt
iziproxy-0.6.0.dist-info/RECORD
