Metadata-Version: 2.4
Name: iziproxy
Version: 0.6.0
Summary: Une bibliothèque Python pour la gestion simplifiée des proxys d'entreprise
Author: sanjuant
License: MIT License
Project-URL: Homepage, https://github.com/sanjuant/iziproxy
Project-URL: Bug Tracker, https://github.com/sanjuant/iziproxy/issues
Keywords: proxy,enterprise,authentication,ntlm,requests,configuration,development,pac
Classifier: Programming Language :: Python :: 3
Classifier: License :: OSI Approved :: MIT License
Classifier: Operating System :: OS Independent
Classifier: Development Status :: 4 - Beta
Classifier: Intended Audience :: Developers
Classifier: Topic :: Internet :: Proxy Servers
Classifier: Topic :: Software Development :: Libraries :: Python Modules
Requires-Python: >=3.7
License-File: LICENSE
Requires-Dist: requests>=2.25.0
Requires-Dist: PyYAML>=6.0
Requires-Dist: keyring>=23.0.0
Requires-Dist: cryptography>=36.0.0
Requires-Dist: importlib_metadata>=4.0.0; python_version < "3.8"
Provides-Extra: ntlm
Requires-Dist: ntlm-auth>=1.5.0; extra == "ntlm"
Requires-Dist: pycryptodomex>=3.14.1; extra == "ntlm"
Provides-Extra: dev
Requires-Dist: pytest>=6.0.0; extra == "dev"
Requires-Dist: pytest-cov>=2.12.0; extra == "dev"
Requires-Dist: black>=22.0.0; extra == "dev"
Requires-Dist: flake8>=4.0.0; extra == "dev"
Requires-Dist: sphinx>=4.0.0; extra == "dev"
Requires-Dist: sphinx-rtd-theme>=1.0.0; extra == "dev"
Dynamic: license-file
